vagabond/__init__.py
vagabond/environmental.py
vagabond/systems.py
py_vagabond-2.0.2.dist-info/LICENSE.rst
py_vagabond-2.0.2.dist-info/METADATA
py_vagabond-2.0.2.dist-info/WHEEL
py_vagabond-2.0.2.dist-info/top_level.txt
py_vagabond-2.0.2.dist-info/RECORD
