Metadata-Version: 2.1
Name: py-vagabond
Version: 2.0.2
Summary: Vagabond is a comprehensive library for pathfinding, navigation, and environmental understanding in robotics and automation. It provides a range of algorithms and tools to help developers create efficient and sophisticated pathfinding solutions for robots and autonomous systems.
Home-page: https://github.com/Kawai-Senpai/Vagabond
Download-URL: https://github.com/Kawai-Senpai/Vagabond
Author: Ranit Bhowmick
Author-email: bhowmickranitking@duck.com
License: MIT License with attribution requirement
Keywords: Pathfinding,Robotics,Navigation,A* Algorithm,Graph Theory,Automation,Robotic Systems
License-File: LICENSE.rst
Requires-Dist: graphviz (==0.20.1)
